Metadata-Version: 2.1
Name: kinggen
Version: 0.0.2
Summary: Kinggen wrapper in python
Home-page: UNKNOWN
Author: yeeter
License: MIT
Keywords: kinggen
Platform: UNKNOWN
Classifier: Development Status :: 5 - Production/Stable
Classifier: Intended Audience :: Developers
Classifier: Operating System :: Microsoft :: Windows :: Windows 10
Classifier: License :: OSI Approved :: MIT License
Classifier: Programming Language :: Python :: 3
